{
"meta":{"test_sets":[],"test_metrics":[],"learn_metrics":[{"best_value":"Min","name":"RMSE"}],"launch_mode":"Train","parameters":"","iteration_count":10,"learn_sets":["learn"],"name":"experiment"},
"iterations":[
{"learn":[0.681245825],"iteration":0,"passed_time":0.1764214236,"remaining_time":1.587792813},
{"learn":[0.6791785582],"iteration":1,"passed_time":0.1912548532,"remaining_time":0.7650194127},
{"learn":[0.6774625529],"iteration":2,"passed_time":0.2043273654,"remaining_time":0.4767638526},
{"learn":[0.6758805435],"iteration":3,"passed_time":0.2191630335,"remaining_time":0.3287445503},
{"learn":[0.6744562097],"iteration":4,"passed_time":0.2324947476,"remaining_time":0.2324947476},
{"learn":[0.6731958355],"iteration":5,"passed_time":0.2459688871,"remaining_time":0.1639792581},
{"learn":[0.6721550457],"iteration":6,"passed_time":0.2574032367,"remaining_time":0.1103156729},
{"learn":[0.6706436818],"iteration":7,"passed_time":0.2661207259,"remaining_time":0.06653018147},
{"learn":[0.6698202361],"iteration":8,"passed_time":0.2738579902,"remaining_time":0.03042866558},
{"learn":[0.6690618387],"iteration":9,"passed_time":0.2792693946,"remaining_time":0}
]}